{"nodes": [
{"id": "Arclight Phoenix", "group": 1},
{"id": "Burn", "group": 1},
{"id": "Canadian Threshold", "group": 1},
{"id": "Death and taxes", "group": 1},
{"id": "Death's Shadow", "group": 1},
{"id": "Delver (Other)", "group": 1},
{"id": "Dragon Stompy", "group": 1},
{"id": "Eldrazi Aggro", "group": 1},
{"id": "Goblins", "group": 1},
{"id": "Grixis Delver", "group": 1},
{"id": "Humans", "group": 1},
{"id": "Maverick", "group": 1},
{"id": "Merfolk", "group": 1},
{"id": "Pikula", "group": 1},
{"id": "Slivers", "group": 1},
{"id": "UR Delver", "group": 1},
{"id": "Zombie Bombardment", "group": 1},
{"id": "Belcher", "group": 2},
{"id": "Bomberman", "group": 2},
{"id": "Cloudpost Ramp", "group": 2},
{"id": "Dark Depths", "group": 2},
{"id": "Doomsday", "group": 2},
{"id": "Dredge", "group": 2},
{"id": "Elves", "group": 2},
{"id": "Food Chain", "group": 2},
{"id": "Infect", "group": 2},
{"id": "Painter", "group": 2},
{"id": "Reanimator", "group": 2},
{"id": "Sneak & Show", "group": 2},
{"id": "Storm", "group": 2},
{"id": "4-c Control", "group": 3},
{"id": "Antiquities War", "group": 3},
{"id": "BUG Midrange", "group": 3},
{"id": "Grixis Control", "group": 3},
{"id": "Junk", "group": 3},
{"id": "Lands", "group": 3},
{"id": "Legacy Landstill", "group": 3},
{"id": "LOAM", "group": 3},
{"id": "Nic Fit", "group": 3},
{"id": "Stoneblade", "group": 3},
{"id": "UWx Control", "group": 3}],
"links": [{"source": "4-c Control", "target": "Arclight Phoenix", "value":0.5347826086956523},
    {"source": "4-c Control", "target": "BUG Midrange", "value":0.43103448275862066},
    {"source": "4-c Control", "target": "Burn", "value":0.04932735425067868},
    {"source": "4-c Control", "target": "Canadian Threshold", "value":0.256},
    {"source": "4-c Control", "target": "Dark Depths", "value":0.10779220778653063},
    {"source": "4-c Control", "target": "Death's Shadow", "value":0.31597222222222227},
    {"source": "4-c Control", "target": "Delver (Other)", "value":0.42857142857142855},
    {"source": "4-c Control", "target": "Doomsday", "value":0.5106382978723404},
    {"source": "4-c Control", "target": "Elves", "value":0.11764705880915621},
    {"source": "4-c Control", "target": "Food Chain", "value":0.4727272727272727},
    {"source": "4-c Control", "target": "Goblins", "value":0.023529411764705882},
    {"source": "4-c Control", "target": "Grixis Control", "value":0.4772727272727273},
    {"source": "4-c Control", "target": "Grixis Delver", "value":0.3565217391304348},
    {"source": "4-c Control", "target": "Infect", "value":0.21212121212121213},
    {"source": "4-c Control", "target": "Junk", "value":0.0759493670886076},
    {"source": "4-c Control", "target": "Lands", "value":0.018111254851650715},
    {"source": "4-c Control", "target": "Legacy Landstill", "value":0.04938271604938271},
    {"source": "4-c Control", "target": "LOAM", "value":0.0926640926633771},
    {"source": "4-c Control", "target": "Maverick", "value":0.03187250995320709},
    {"source": "4-c Control", "target": "Nic Fit", "value":0.1097560975636526},
    {"source": "4-c Control", "target": "Pikula", "value":0.07692307692307693},
    {"source": "4-c Control", "target": "Reanimator", "value":0.20224719099532887},
    {"source": "4-c Control", "target": "Sneak & Show", "value":0.18374164813385843},
    {"source": "4-c Control", "target": "Stoneblade", "value":0.12947658402203857},
    {"source": "4-c Control", "target": "Storm", "value":0.5143540669714293},
    {"source": "4-c Control", "target": "UR Delver", "value":0.2183544303797468},
    {"source": "4-c Control", "target": "UWx Control", "value":0.13732394366197184},
    {"source": "4-c Control", "target": "Zombie Bombardment", "value":0.265625},
    {"source": "Affinity", "target": "Antiquities War", "value":0.25},
    {"source": "Affinity", "target": "Bomberman", "value":0.14705882352941177},
    {"source": "Affinity", "target": "Cloudpost Ramp", "value":0.07633587785612728},
    {"source": "Affinity", "target": "Death and taxes", "value":0.040865384615384616},
    {"source": "Affinity", "target": "Dragon Stompy", "value":0.11707317073056514},
    {"source": "Affinity", "target": "Eldrazi Aggro", "value":0.13432835820895522},
    {"source": "Affinity", "target": "Humans", "value":0.025},
    {"source": "Affinity", "target": "Junk", "value":0.024390243902439025},
    {"source": "Affinity", "target": "Lands", "value":0.029023746694390878},
    {"source": "Affinity", "target": "Legacy Landstill", "value":0.10526315789473684},
    {"source": "Affinity", "target": "LOAM", "value":0.021897810218818262},
    {"source": "Affinity", "target": "Maverick", "value":0.02400000000096},
    {"source": "Affinity", "target": "MUD", "value":0.1917808219178082},
    {"source": "Affinity", "target": "Nic Fit", "value":0.02272727272778926},
    {"source": "Affinity", "target": "Painter", "value":0.20588235294117646},
    {"source": "Affinity", "target": "Pikula", "value":0.024691358024691357},
    {"source": "Affinity", "target": "Slivers", "value":0.025},
    {"source": "Affinity", "target": "Sneak & Show", "value":0.07802874743025018},
    {"source": "Antiquities War", "target": "Bomberman", "value":0.11428571428571428},
    {"source": "Antiquities War", "target": "Cloudpost Ramp", "value":0.05223880596346626},
    {"source": "Antiquities War", "target": "Dragon Stompy", "value":0.11707317073056514},
    {"source": "Antiquities War", "target": "Eldrazi Aggro", "value":0.09615384615384615},
    {"source": "Antiquities War", "target": "MUD", "value":0.16},
    {"source": "Antiquities War", "target": "Painter", "value":0.36666666666666664},
    {"source": "Antiquities War", "target": "Sneak & Show", "value":0.07802874743025015},
    {"source": "Arclight Phoenix", "target": "BUG Midrange", "value":0.3113553113553114},
    {"source": "Arclight Phoenix", "target": "Canadian Threshold", "value":0.2003577817531306},
    {"source": "Arclight Phoenix", "target": "Dark Depths", "value":0.03933518006007014},
    {"source": "Arclight Phoenix", "target": "Death's Shadow", "value":0.24806201550387602},
    {"source": "Arclight Phoenix", "target": "Delver (Other)", "value":0.40573770491803285},
    {"source": "Arclight Phoenix", "target": "Doomsday", "value":0.47524752475247534},
    {"source": "Arclight Phoenix", "target": "Food Chain", "value":0.34883720930232565},
    {"source": "Arclight Phoenix", "target": "Grixis Control", "value":0.49252136752136755},
    {"source": "Arclight Phoenix", "target": "Grixis Delver", "value":0.3675564681724847},
    {"source": "Arclight Phoenix", "target": "Infect", "value":0.0888888888888889},
    {"source": "Arclight Phoenix", "target": "Junk", "value":0.04545454545454546},
    {"source": "Arclight Phoenix", "target": "Legacy Landstill", "value":0.09523809523809525},
    {"source": "Arclight Phoenix", "target": "LOAM", "value":0.043624161064704285},
    {"source": "Arclight Phoenix", "target": "Nic Fit", "value":0.05105633802026509},
    {"source": "Arclight Phoenix", "target": "Pikula", "value":0.05830903790087464},
    {"source": "Arclight Phoenix", "target": "Reanimator", "value":0.1797900262456858},
    {"source": "Arclight Phoenix", "target": "Sneak & Show", "value":0.19300991134525833},
    {"source": "Arclight Phoenix", "target": "Stoneblade", "value":0.18060200668896323},
    {"source": "Arclight Phoenix", "target": "Storm", "value":0.5136986301545788},
    {"source": "Arclight Phoenix", "target": "UR Delver", "value":0.2519083969465649},
    {"source": "Arclight Phoenix", "target": "UWx Control", "value":0.21188291830493666},
    {"source": "Arclight Phoenix", "target": "Zombie Bombardment", "value":0.2167832167832168},
    {"source": "Belcher", "target": "Lands", "value":0.028000000001008003},
    {"source": "Bomberman", "target": "Cloudpost Ramp", "value":0.10399999999366402},
    {"source": "Bomberman", "target": "Death and taxes", "value":0.11315789473684208},
    {"source": "Bomberman", "target": "Dragon Stompy", "value":0.2742857142825796},
    {"source": "Bomberman", "target": "Eldrazi Aggro", "value":0.24581005586592172},
    {"source": "Bomberman", "target": "Elves", "value":0.0530973451308638},
    {"source": "Bomberman", "target": "Goblins", "value":0.12},
    {"source": "Bomberman", "target": "Humans", "value":0.17647058823529413},
    {"source": "Bomberman", "target": "Junk", "value":0.05128205128205128},
    {"source": "Bomberman", "target": "Lands", "value":0.02680965146416635},
    {"source": "Bomberman", "target": "Legacy Landstill", "value":0.05128205128205128},
    {"source": "Bomberman", "target": "LOAM", "value":0.02238805970132546},
    {"source": "Bomberman", "target": "Maverick", "value":0.05932203389184144},
    {"source": "Bomberman", "target": "Merfolk", "value":0.08333333333333333},
    {"source": "Bomberman", "target": "MUD", "value":0.3492063492063492},
    {"source": "Bomberman", "target": "Nic Fit", "value":0.1000000000025},
    {"source": "Bomberman", "target": "Painter", "value":0.21212121212121213},
    {"source": "Bomberman", "target": "Pikula", "value":0.05194805194805195},
    {"source": "Bomberman", "target": "Slivers", "value":0.17647058823529413},
    {"source": "Bomberman", "target": "Sneak & Show", "value":0.1302428255906564},
    {"source": "Bomberman", "target": "Stoneblade", "value":0.04221635883905013},
    {"source": "Bomberman", "target": "UWx Control", "value":0.03150912106135987},
    {"source": "BUG Midrange", "target": "Canadian Threshold", "value":0.21374045801526717},
    {"source": "BUG Midrange", "target": "Cloudpost Ramp", "value":0.021276595745133547},
    {"source": "BUG Midrange", "target": "Dark Depths", "value":0.16486486489504015},
    {"source": "BUG Midrange", "target": "Death and taxes", "value":0.027842227378190264},
    {"source": "BUG Midrange", "target": "Death's Shadow", "value":0.2673267326732674},
    {"source": "BUG Midrange", "target": "Delver (Other)", "value":0.4727272727272727},
    {"source": "BUG Midrange", "target": "Doomsday", "value":0.3333333333333333},
    {"source": "BUG Midrange", "target": "Elves", "value":0.17370892019228987},
    {"source": "BUG Midrange", "target": "Food Chain", "value":0.673469387755102},
    {"source": "BUG Midrange", "target": "Grixis Control", "value":0.22304832713754646},
    {"source": "BUG Midrange", "target": "Grixis Delver", "value":0.234375},
    {"source": "BUG Midrange", "target": "Infect", "value":0.39655172413793105},
    {"source": "BUG Midrange", "target": "Junk", "value":0.16216216216216217},
    {"source": "BUG Midrange", "target": "Lands", "value":0.05585106383112409},
    {"source": "BUG Midrange", "target": "Legacy Landstill", "value":0.04878048780487805},
    {"source": "BUG Midrange", "target": "LOAM", "value":0.16734693876461476},
    {"source": "BUG Midrange", "target": "Maverick", "value":0.08264462809364113},
    {"source": "BUG Midrange", "target": "Merfolk", "value":0.05128205128205128},
    {"source": "BUG Midrange", "target": "Nic Fit", "value":0.21052631579501385},
    {"source": "BUG Midrange", "target": "Painter", "value":0.037037037037037035},
    {"source": "BUG Midrange", "target": "Pikula", "value":0.11842105263157894},
    {"source": "BUG Midrange", "target": "Reanimator", "value":0.12435233159719723},
    {"source": "BUG Midrange", "target": "Sneak & Show", "value":0.12317327767692346},
    {"source": "BUG Midrange", "target": "Stoneblade", "value":0.1592178770949721},
    {"source": "BUG Midrange", "target": "Storm", "value":0.40174672488911356},
    {"source": "BUG Midrange", "target": "UR Delver", "value":0.15384615384615385},
    {"source": "BUG Midrange", "target": "UWx Control", "value":0.1373913043478261},
    {"source": "BUG Midrange", "target": "Zombie Bombardment", "value":0.18840579710144928},
    {"source": "Burn", "target": "Canadian Threshold", "value":0.027586206896551724},
    {"source": "Burn", "target": "Death's Shadow", "value":0.046647230320699715},
    {"source": "Burn", "target": "Doomsday", "value":0.05235602095342781},
    {"source": "Burn", "target": "Dragon Stompy", "value":0.3580246913703704},
    {"source": "Burn", "target": "Elves", "value":0.035242290738535575},
    {"source": "Burn", "target": "Goblins", "value":0.27692307692307694},
    {"source": "Burn", "target": "Grixis Control", "value":0.05460750853242321},
    {"source": "Burn", "target": "Grixis Delver", "value":0.030162412983478774},
    {"source": "Burn", "target": "Lands", "value":0.02567567567352812},
    {"source": "Burn", "target": "Legacy Landstill", "value":0.034042553182689},
    {"source": "Burn", "target": "Maverick", "value":0.042194092837579446},
    {"source": "Burn", "target": "Reanimator", "value":0.06315789476576177},
    {"source": "Burn", "target": "Sneak & Show", "value":0.02709109378524643},
    {"source": "Burn", "target": "Storm", "value":0.041884816743894084},
    {"source": "Burn", "target": "UR Delver", "value":0.06517509726590297},
    {"source": "Burn", "target": "UWx Control", "value":0.029050279320410727},
    {"source": "Burn", "target": "Zombie Bombardment", "value":0.04524886878773981},
    {"source": "Canadian Threshold", "target": "Dark Depths", "value":0.04317460317615601},
    {"source": "Canadian Threshold", "target": "Death and taxes", "value":0.10512483574244413},
    {"source": "Canadian Threshold", "target": "Death's Shadow", "value":0.2910714285714286},
    {"source": "Canadian Threshold", "target": "Delver (Other)", "value":0.36607142857142855},
    {"source": "Canadian Threshold", "target": "Doomsday", "value":0.18421052631578946},
    {"source": "Canadian Threshold", "target": "Eldrazi Aggro", "value":0.05721096543504172},
    {"source": "Canadian Threshold", "target": "Elves", "value":0.06053811658975647},
    {"source": "Canadian Threshold", "target": "Food Chain", "value":0.19230769230769232},
    {"source": "Canadian Threshold", "target": "Goblins", "value":0.12080536912751678},
    {"source": "Canadian Threshold", "target": "Grixis Control", "value":0.14760147601476015},
    {"source": "Canadian Threshold", "target": "Grixis Delver", "value":0.49},
    {"source": "Canadian Threshold", "target": "Humans", "value":0.11188811188811189},
    {"source": "Canadian Threshold", "target": "Infect", "value":0.11678832116788321},
    {"source": "Canadian Threshold", "target": "Junk", "value":0.10884353741496598},
    {"source": "Canadian Threshold", "target": "Lands", "value":0.11558156547814433},
    {"source": "Canadian Threshold", "target": "Legacy Landstill", "value":0.07947019867549669},
    {"source": "Canadian Threshold", "target": "LOAM", "value":0.11680327868756718},
    {"source": "Canadian Threshold", "target": "Maverick", "value":0.12954545455134298},
    {"source": "Canadian Threshold", "target": "Merfolk", "value":0.040268456375838924},
    {"source": "Canadian Threshold", "target": "MUD", "value":0.09032258064516129},
    {"source": "Canadian Threshold", "target": "Pikula", "value":0.09523809523809523},
    {"source": "Canadian Threshold", "target": "Reanimator", "value":0.06824146982247298},
    {"source": "Canadian Threshold", "target": "Sneak & Show", "value":0.22148859542965083},
    {"source": "Canadian Threshold", "target": "Stoneblade", "value":0.26003210272873195},
    {"source": "Canadian Threshold", "target": "Storm", "value":0.19582504969695147},
    {"source": "Canadian Threshold", "target": "UR Delver", "value":0.40804597701149425},
    {"source": "Canadian Threshold", "target": "UWx Control", "value":0.19767441860465115},
    {"source": "Canadian Threshold", "target": "Zombie Bombardment", "value":0.0763888888888889},
    {"source": "Cloudpost Ramp", "target": "Dark Depths", "value":0.08988764046148212},
    {"source": "Cloudpost Ramp", "target": "Death and taxes", "value":0.03356164382922687},
    {"source": "Cloudpost Ramp", "target": "Dragon Stompy", "value":0.0796812748930652},
    {"source": "Cloudpost Ramp", "target": "Eldrazi Aggro", "value":0.2934426229156276},
    {"source": "Cloudpost Ramp", "target": "Elves", "value":0.08333333331628787},
    {"source": "Cloudpost Ramp", "target": "Food Chain", "value":0.0217391304352552},
    {"source": "Cloudpost Ramp", "target": "Humans", "value":0.02857142856469388},
    {"source": "Cloudpost Ramp", "target": "Infect", "value":0.04494382022572908},
    {"source": "Cloudpost Ramp", "target": "Junk", "value":0.04999999999357144},
    {"source": "Cloudpost Ramp", "target": "Lands", "value":0.12660393500007686},
    {"source": "Cloudpost Ramp", "target": "Legacy Landstill", "value":0.020833333333767363},
    {"source": "Cloudpost Ramp", "target": "LOAM", "value":0.08783783783167458},
    {"source": "Cloudpost Ramp", "target": "Maverick", "value":0.09558823526751732},
    {"source": "Cloudpost Ramp", "target": "MUD", "value":0.19762845849324318},
    {"source": "Cloudpost Ramp", "target": "Nic Fit", "value":0.11428571428265306},
    {"source": "Cloudpost Ramp", "target": "Painter", "value":0.07462686566529295},
    {"source": "Cloudpost Ramp", "target": "Pikula", "value":0.02826855123008154},
    {"source": "Cloudpost Ramp", "target": "Reanimator", "value":0.03265306121499375},
    {"source": "Cloudpost Ramp", "target": "Slivers", "value":0.021276595745133547},
    {"source": "Cloudpost Ramp", "target": "Sneak & Show", "value":0.07566938299641002},
    {"source": "Dark Depths", "target": "Death and taxes", "value":0.055127306697824036},
    {"source": "Dark Depths", "target": "Death's Shadow", "value":0.08551198257143353},
    {"source": "Dark Depths", "target": "Delver (Other)", "value":0.10449735449751196},
    {"source": "Dark Depths", "target": "Doomsday", "value":0.03005464482762251},
    {"source": "Dark Depths", "target": "Eldrazi Aggro", "value":0.06732941707695293},
    {"source": "Dark Depths", "target": "Elves", "value":0.13227513227941545},
    {"source": "Dark Depths", "target": "Food Chain", "value":0.1374663073107141},
    {"source": "Dark Depths", "target": "Goblins", "value":0.03815028900925791},
    {"source": "Dark Depths", "target": "Grixis Delver", "value":0.04342273307946155},
    {"source": "Dark Depths", "target": "Humans", "value":0.04611650485071047},
    {"source": "Dark Depths", "target": "Infect", "value":0.1549100968368887},
    {"source": "Dark Depths", "target": "Junk", "value":0.16710875333907926},
    {"source": "Dark Depths", "target": "Lands", "value":0.2755498059567716},
    {"source": "Dark Depths", "target": "LOAM", "value":0.27176780997344063},
    {"source": "Dark Depths", "target": "Maverick", "value":0.1319796954130356},
    {"source": "Dark Depths", "target": "Merfolk", "value":0.029268292674681732},
    {"source": "Dark Depths", "target": "MUD", "value":0.02718006794257453},
    {"source": "Dark Depths", "target": "Nic Fit", "value":0.23544973548179637},
    {"source": "Dark Depths", "target": "Pikula", "value":0.10955414013025111},
    {"source": "Dark Depths", "target": "Reanimator", "value":0.09869375909731819},
    {"source": "Dark Depths", "target": "Stoneblade", "value":0.055693069305552144},
    {"source": "Dark Depths", "target": "Storm", "value":0.05056179777880003},
    {"source": "Dark Depths", "target": "UR Delver", "value":0.04258064515211987},
    {"source": "Dark Depths", "target": "Zombie Bombardment", "value":0.06030150754416556},
    {"source": "Death and taxes", "target": "Death's Shadow", "value":0.09115281501340483},
    {"source": "Death and taxes", "target": "Delver (Other)", "value":0.10880829015544044},
    {"source": "Death and taxes", "target": "Eldrazi Aggro", "value":0.11643835616438354},
    {"source": "Death and taxes", "target": "Elves", "value":0.07148659625217357},
    {"source": "Death and taxes", "target": "Goblins", "value":0.2513513513513514},
    {"source": "Death and taxes", "target": "Grixis Delver", "value":0.10582010582010581},
    {"source": "Death and taxes", "target": "Humans", "value":0.20380434782608697},
    {"source": "Death and taxes", "target": "Infect", "value":0.05159705159705161},
    {"source": "Death and taxes", "target": "Junk", "value":0.20478723404255325},
    {"source": "Death and taxes", "target": "Lands", "value":0.19878119560123797},
    {"source": "Death and taxes", "target": "Legacy Landstill", "value":0.08373205741626795},
    {"source": "Death and taxes", "target": "LOAM", "value":0.14427480915920401},
    {"source": "Death and taxes", "target": "Maverick", "value":0.20226678291027958},
    {"source": "Death and taxes", "target": "Merfolk", "value":0.0638820638820639},
    {"source": "Death and taxes", "target": "MUD", "value":0.11428571428571427},
    {"source": "Death and taxes", "target": "Nic Fit", "value":0.10864575362828838},
    {"source": "Death and taxes", "target": "Pikula", "value":0.1727748691099477},
    {"source": "Death and taxes", "target": "Slivers", "value":0.07524271844660195},
    {"source": "Death and taxes", "target": "Stoneblade", "value":0.13178294573643412},
    {"source": "Death and taxes", "target": "UR Delver", "value":0.10427807486631015},
    {"source": "Death and taxes", "target": "UWx Control", "value":0.0807259073842303},
    {"source": "Death's Shadow", "target": "Delver (Other)", "value":0.45849802371541515},
    {"source": "Death's Shadow", "target": "Doomsday", "value":0.3278688524590164},
    {"source": "Death's Shadow", "target": "Eldrazi Aggro", "value":0.059113300492610835},
    {"source": "Death's Shadow", "target": "Elves", "value":0.07330827067393578},
    {"source": "Death's Shadow", "target": "Food Chain", "value":0.2550335570469799},
    {"source": "Death's Shadow", "target": "Goblins", "value":0.11602209944751384},
    {"source": "Death's Shadow", "target": "Grixis Control", "value":0.21341956345998386},
    {"source": "Death's Shadow", "target": "Grixis Delver", "value":0.3781190019193859},
    {"source": "Death's Shadow", "target": "Humans", "value":0.09090909090909093},
    {"source": "Death's Shadow", "target": "Infect", "value":0.125},
    {"source": "Death's Shadow", "target": "Junk", "value":0.152046783625731},
    {"source": "Death's Shadow", "target": "Lands", "value":0.07955865272519427},
    {"source": "Death's Shadow", "target": "Legacy Landstill", "value":0.03141361256544503},
    {"source": "Death's Shadow", "target": "LOAM", "value":0.13769363165855944},
    {"source": "Death's Shadow", "target": "Maverick", "value":0.12336448598707311},
    {"source": "Death's Shadow", "target": "Merfolk", "value":0.05352112676056338},
    {"source": "Death's Shadow", "target": "MUD", "value":0.08488063660477455},
    {"source": "Death's Shadow", "target": "Nic Fit", "value":0.07432432431713384},
    {"source": "Death's Shadow", "target": "Pikula", "value":0.18960244648318045},
    {"source": "Death's Shadow", "target": "Reanimator", "value":0.16726403823173736},
    {"source": "Death's Shadow", "target": "Sneak & Show", "value":0.11992704061039572},
    {"source": "Death's Shadow", "target": "Stoneblade", "value":0.22258064516129028},
    {"source": "Death's Shadow", "target": "Storm", "value":0.3238532109937969},
    {"source": "Death's Shadow", "target": "UR Delver", "value":0.2688172043010753},
    {"source": "Death's Shadow", "target": "UWx Control", "value":0.1291177584248391},
    {"source": "Death's Shadow", "target": "Zombie Bombardment", "value":0.21428571428571433},
    {"source": "Delver (Other)", "target": "Doomsday", "value":0.38},
    {"source": "Delver (Other)", "target": "Eldrazi Aggro", "value":0.056206088992974246},
    {"source": "Delver (Other)", "target": "Elves", "value":0.1004566210109464},
    {"source": "Delver (Other)", "target": "Food Chain", "value":0.49056603773584906},
    {"source": "Delver (Other)", "target": "Goblins", "value":0.1038961038961039},
    {"source": "Delver (Other)", "target": "Grixis Control", "value":0.27309236947791166},
    {"source": "Delver (Other)", "target": "Grixis Delver", "value":0.46153846153846156},
    {"source": "Delver (Other)", "target": "Humans", "value":0.1095890410958904},
    {"source": "Delver (Other)", "target": "Infect", "value":0.21875},
    {"source": "Delver (Other)", "target": "Junk", "value":0.16901408450704225},
    {"source": "Delver (Other)", "target": "Lands", "value":0.09957325747054385},
    {"source": "Delver (Other)", "target": "Legacy Landstill", "value":0.05063291139240506},
    {"source": "Delver (Other)", "target": "LOAM", "value":0.15899581588855238},
    {"source": "Delver (Other)", "target": "Maverick", "value":0.14479638008668944},
    {"source": "Delver (Other)", "target": "Merfolk", "value":0.06756756756756757},
    {"source": "Delver (Other)", "target": "MUD", "value":0.08860759493670886},
    {"source": "Delver (Other)", "target": "Nic Fit", "value":0.08536585366061868},
    {"source": "Delver (Other)", "target": "Painter", "value":0.02531645569620253},
    {"source": "Delver (Other)", "target": "Pikula", "value":0.15492957746478872},
    {"source": "Delver (Other)", "target": "Reanimator", "value":0.11229946523223426},
    {"source": "Delver (Other)", "target": "Sneak & Show", "value":0.12840043527150552},
    {"source": "Delver (Other)", "target": "Stoneblade", "value":0.22324159021406725},
    {"source": "Delver (Other)", "target": "Storm", "value":0.44028103043035394},
    {"source": "Delver (Other)", "target": "UR Delver", "value":0.2975778546712803},
    {"source": "Delver (Other)", "target": "UWx Control", "value":0.1371841155234657},
    {"source": "Delver (Other)", "target": "Zombie Bombardment", "value":0.14492753623188406},
    {"source": "Doomsday", "target": "Elves", "value":0.049019607851499426},
    {"source": "Doomsday", "target": "Food Chain", "value":0.4583333333333333},
    {"source": "Doomsday", "target": "Goblins", "value":0.02702702702702703},
    {"source": "Doomsday", "target": "Grixis Control", "value":0.5786516853932584},
    {"source": "Doomsday", "target": "Grixis Delver", "value":0.30097087378640774},
    {"source": "Doomsday", "target": "Infect", "value":0.09523809523809523},
    {"source": "Doomsday", "target": "Junk", "value":0.027777777777777776},
    {"source": "Doomsday", "target": "Legacy Landstill", "value":0.05714285714285714},
    {"source": "Doomsday", "target": "LOAM", "value":0.02459016393422467},
    {"source": "Doomsday", "target": "Merfolk", "value":0.06060606060606061},
    {"source": "Doomsday", "target": "Nic Fit", "value":0.052631578948753456},
    {"source": "Doomsday", "target": "Painter", "value":0.058823529411764705},
    {"source": "Doomsday", "target": "Pikula", "value":0.057971014492753624},
    {"source": "Doomsday", "target": "Reanimator", "value":0.24827586204499405},
    {"source": "Doomsday", "target": "Sneak & Show", "value":0.18863049097820642},
    {"source": "Doomsday", "target": "Stoneblade", "value":0.16393442622950818},
    {"source": "Doomsday", "target": "Storm", "value":0.8040540540622718},
    {"source": "Doomsday", "target": "UR Delver", "value":0.22676579925650558},
    {"source": "Doomsday", "target": "UWx Control", "value":0.17721518987341772},
    {"source": "Doomsday", "target": "Zombie Bombardment", "value":0.2962962962962963},
    {"source": "Dragon Stompy", "target": "Eldrazi Aggro", "value":0.15276558384413721},
    {"source": "Dragon Stompy", "target": "Goblins", "value":0.20487804877848897},
    {"source": "Dragon Stompy", "target": "MUD", "value":0.2376237623738849},
    {"source": "Dragon Stompy", "target": "Painter", "value":0.21761658030862574},
    {"source": "Dragon Stompy", "target": "Sneak & Show", "value":0.15431861800966337},
    {"source": "Eldrazi Aggro", "target": "Elves", "value":0.045180722890205395},
    {"source": "Eldrazi Aggro", "target": "Goblins", "value":0.11212814645308924},
    {"source": "Eldrazi Aggro", "target": "Grixis Delver", "value":0.05755395683453238},
    {"source": "Eldrazi Aggro", "target": "Humans", "value":0.13106796116504854},
    {"source": "Eldrazi Aggro", "target": "Infect", "value":0.02267573696145125},
    {"source": "Eldrazi Aggro", "target": "Junk", "value":0.07692307692307691},
    {"source": "Eldrazi Aggro", "target": "Lands", "value":0.072999999993595},
    {"source": "Eldrazi Aggro", "target": "Legacy Landstill", "value":0.0303030303030303},
    {"source": "Eldrazi Aggro", "target": "LOAM", "value":0.07397260273921935},
    {"source": "Eldrazi Aggro", "target": "Maverick", "value":0.08872180450642772},
    {"source": "Eldrazi Aggro", "target": "Merfolk", "value":0.0831353919239905},
    {"source": "Eldrazi Aggro", "target": "MUD", "value":0.4149855907780979},
    {"source": "Eldrazi Aggro", "target": "Nic Fit", "value":0.06302521008535768},
    {"source": "Eldrazi Aggro", "target": "Painter", "value":0.14215686274509803},
    {"source": "Eldrazi Aggro", "target": "Pikula", "value":0.07780320366132723},
    {"source": "Eldrazi Aggro", "target": "Slivers", "value":0.06880733944954127},
    {"source": "Eldrazi Aggro", "target": "Sneak & Show", "value":0.10950259835336948},
    {"source": "Eldrazi Aggro", "target": "Stoneblade", "value":0.0671296296296296},
    {"source": "Eldrazi Aggro", "target": "UR Delver", "value":0.058252427184466014},
    {"source": "Elves", "target": "Food Chain", "value":0.15094339624243505},
    {"source": "Elves", "target": "Goblins", "value":0.060728744937304326},
    {"source": "Elves", "target": "Grixis Delver", "value":0.03296703296587368},
    {"source": "Elves", "target": "Humans", "value":0.06837606838286214},
    {"source": "Elves", "target": "Infect", "value":0.28877005346358203},
    {"source": "Elves", "target": "Junk", "value":0.230769230760355},
    {"source": "Elves", "target": "Lands", "value":0.09629629628808642},
    {"source": "Elves", "target": "LOAM", "value":0.18333333334541663},
    {"source": "Elves", "target": "Maverick", "value":0.32653061222115787},
    {"source": "Elves", "target": "Merfolk", "value":0.04273504274249398},
    {"source": "Elves", "target": "MUD", "value":0.03921568628143021},
    {"source": "Elves", "target": "Nic Fit", "value":0.3564356436011175},
    {"source": "Elves", "target": "Pikula", "value":0.07659574467824354},
    {"source": "Elves", "target": "Reanimator", "value":0.033653846160225584},
    {"source": "Elves", "target": "Slivers", "value":0.05042016806553209},
    {"source": "Elves", "target": "Stoneblade", "value":0.03868797307659008},
    {"source": "Elves", "target": "Storm", "value":0.07432432434096511},
    {"source": "Elves", "target": "Zombie Bombardment", "value":0.03389830507483481},
    {"source": "Food Chain", "target": "Grixis Control", "value":0.3155737704918033},
    {"source": "Food Chain", "target": "Grixis Delver", "value":0.18461538461538463},
    {"source": "Food Chain", "target": "Infect", "value":0.3389830508474576},
    {"source": "Food Chain", "target": "Junk", "value":0.10526315789473684},
    {"source": "Food Chain", "target": "Lands", "value":0.03723404255408273},
    {"source": "Food Chain", "target": "Legacy Landstill", "value":0.05},
    {"source": "Food Chain", "target": "LOAM", "value":0.12903225805437046},
    {"source": "Food Chain", "target": "Maverick", "value":0.05785123966306945},
    {"source": "Food Chain", "target": "Merfolk", "value":0.05263157894736842},
    {"source": "Food Chain", "target": "Nic Fit", "value":0.21621621622205986},
    {"source": "Food Chain", "target": "Painter", "value":0.05128205128205128},
    {"source": "Food Chain", "target": "Pikula", "value":0.12162162162162163},
    {"source": "Food Chain", "target": "Reanimator", "value":0.16574585634077102},
    {"source": "Food Chain", "target": "Sneak & Show", "value":0.12660944207565067},
    {"source": "Food Chain", "target": "Stoneblade", "value":0.14084507042253522},
    {"source": "Food Chain", "target": "Storm", "value":0.5145631068258084},
    {"source": "Food Chain", "target": "UR Delver", "value":0.14114114114114115},
    {"source": "Food Chain", "target": "UWx Control", "value":0.12920353982300886},
    {"source": "Food Chain", "target": "Zombie Bombardment", "value":0.21212121212121213},
    {"source": "Goblins", "target": "Grixis Control", "value":0.02373887240356083},
    {"source": "Goblins", "target": "Grixis Delver", "value":0.1292517006802721},
    {"source": "Goblins", "target": "Humans", "value":0.23943661971830985},
    {"source": "Goblins", "target": "Infect", "value":0.024096385542168676},
    {"source": "Goblins", "target": "Junk", "value":0.1111111111111111},
    {"source": "Goblins", "target": "Lands", "value":0.18103448276330264},
    {"source": "Goblins", "target": "Legacy Landstill", "value":0.022727272727272728},
    {"source": "Goblins", "target": "LOAM", "value":0.0996309963092278},
    {"source": "Goblins", "target": "Maverick", "value":0.1322314049547845},
    {"source": "Goblins", "target": "Merfolk", "value":0.11688311688311688},
    {"source": "Goblins", "target": "MUD", "value":0.1625},
    {"source": "Goblins", "target": "Nic Fit", "value":0.054945054946262534},
    {"source": "Goblins", "target": "Pikula", "value":0.09876543209876543},
    {"source": "Goblins", "target": "Reanimator", "value":0.036199095039086006},
    {"source": "Goblins", "target": "Slivers", "value":0.11392405063291139},
    {"source": "Goblins", "target": "Stoneblade", "value":0.08208955223880594},
    {"source": "Goblins", "target": "Storm", "value":0.027272727273223142},
    {"source": "Goblins", "target": "UR Delver", "value":0.16477272727272724},
    {"source": "Goblins", "target": "Zombie Bombardment", "value":0.023809523809523808},
    {"source": "Grixis Control", "target": "Grixis Delver", "value":0.37333333333333335},
    {"source": "Grixis Control", "target": "Infect", "value":0.025889967637540454},
    {"source": "Grixis Control", "target": "Junk", "value":0.0243161094224924},
    {"source": "Grixis Control", "target": "Legacy Landstill", "value":0.13087248322147652},
    {"source": "Grixis Control", "target": "LOAM", "value":0.02183803457672911},
    {"source": "Grixis Control", "target": "Merfolk", "value":0.049019607843137254},
    {"source": "Grixis Control", "target": "Nic Fit", "value":0.048402710544796175},
    {"source": "Grixis Control", "target": "Painter", "value":0.04777070063694268},
    {"source": "Grixis Control", "target": "Pikula", "value":0.0707395498392283},
    {"source": "Grixis Control", "target": "Reanimator", "value":0.29907975457553915},
    {"source": "Grixis Control", "target": "Sneak & Show", "value":0.26516516518629546},
    {"source": "Grixis Control", "target": "Stoneblade", "value":0.1459802538787024},
    {"source": "Grixis Control", "target": "Storm", "value":0.47613435474321536},
    {"source": "Grixis Control", "target": "UR Delver", "value":0.3307155322862129},
    {"source": "Grixis Control", "target": "UWx Control", "value":0.1743119266055046},
    {"source": "Grixis Control", "target": "Zombie Bombardment", "value":0.3375},
    {"source": "Grixis Delver", "target": "Humans", "value":0.11267605633802817},
    {"source": "Grixis Delver", "target": "Infect", "value":0.07801418439716312},
    {"source": "Grixis Delver", "target": "Junk", "value":0.1095890410958904},
    {"source": "Grixis Delver", "target": "Lands", "value":0.08273894437040624},
    {"source": "Grixis Delver", "target": "Legacy Landstill", "value":0.1095890410958904},
    {"source": "Grixis Delver", "target": "LOAM", "value":0.09716599190204724},
    {"source": "Grixis Delver", "target": "Maverick", "value":0.1076233183904764},
    {"source": "Grixis Delver", "target": "Merfolk", "value":0.0547945205479452},
    {"source": "Grixis Delver", "target": "MUD", "value":0.09090909090909091},
    {"source": "Grixis Delver", "target": "Nic Fit", "value":0.02352941176525952},
    {"source": "Grixis Delver", "target": "Pikula", "value":0.1111111111111111},
    {"source": "Grixis Delver", "target": "Reanimator", "value":0.08894878705528149},
    {"source": "Grixis Delver", "target": "Sneak & Show", "value":0.3045161290316953},
    {"source": "Grixis Delver", "target": "Stoneblade", "value":0.2786885245901639},
    {"source": "Grixis Delver", "target": "Storm", "value":0.2992383025161901},
    {"source": "Grixis Delver", "target": "UR Delver", "value":0.5665236051502147},
    {"source": "Grixis Delver", "target": "UWx Control", "value":0.206286836935167},
    {"source": "Grixis Delver", "target": "Zombie Bombardment", "value":0.11594202898550725},
    {"source": "Humans", "target": "Infect", "value":0.02531645569620253},
    {"source": "Humans", "target": "Junk", "value":0.16216216216216217},
    {"source": "Humans", "target": "Lands", "value":0.0997229916952832},
    {"source": "Humans", "target": "Legacy Landstill", "value":0.023809523809523808},
    {"source": "Humans", "target": "LOAM", "value":0.11718749999908447},
    {"source": "Humans", "target": "Maverick", "value":0.16964285713998728},
    {"source": "Humans", "target": "Merfolk", "value":0.1232876712328767},
    {"source": "Humans", "target": "MUD", "value":0.17105263157894737},
    {"source": "Humans", "target": "Nic Fit", "value":0.06976744186208762},
    {"source": "Humans", "target": "Pikula", "value":0.11842105263157894},
    {"source": "Humans", "target": "Slivers", "value":0.4482758620689655},
    {"source": "Humans", "target": "Stoneblade", "value":0.07512953367875647},
    {"source": "Humans", "target": "UR Delver", "value":0.1111111111111111},
    {"source": "Infect", "target": "Junk", "value":0.18571428571428572},
    {"source": "Infect", "target": "Lands", "value":0.09180790960993808},
    {"source": "Infect", "target": "Legacy Landstill", "value":0.024691358024691357},
    {"source": "Infect", "target": "LOAM", "value":0.19396551723970717},
    {"source": "Infect", "target": "Maverick", "value":0.16055045871231377},
    {"source": "Infect", "target": "Nic Fit", "value":0.23041474653880947},
    {"source": "Infect", "target": "Pikula", "value":0.09333333333333334},
    {"source": "Infect", "target": "Reanimator", "value":0.02970297029497108},
    {"source": "Infect", "target": "Sneak & Show", "value":0.027750247771831514},
    {"source": "Infect", "target": "Stoneblade", "value":0.07526881720430108},
    {"source": "Infect", "target": "Storm", "value":0.14525139663849446},
    {"source": "Infect", "target": "UR Delver", "value":0.03591160220994475},
    {"source": "Infect", "target": "UWx Control", "value":0.03789126853377265},
    {"source": "Infect", "target": "Zombie Bombardment", "value":0.05333333333333334},
    {"source": "Junk", "target": "Lands", "value":0.16426512969061283},
    {"source": "Junk", "target": "Legacy Landstill", "value":0.047619047619047616},
    {"source": "Junk", "target": "LOAM", "value":0.4038461538827662},
    {"source": "Junk", "target": "Maverick", "value":0.5581395349161709},
    {"source": "Junk", "target": "Merfolk", "value":0.037037037037037035},
    {"source": "Junk", "target": "MUD", "value":0.08333333333333333},
    {"source": "Junk", "target": "Nic Fit", "value":0.3177570093793345},
    {"source": "Junk", "target": "Pikula", "value":0.3384615384615385},
    {"source": "Junk", "target": "Reanimator", "value":0.07211538461053069},
    {"source": "Junk", "target": "Slivers", "value":0.023809523809523808},
    {"source": "Junk", "target": "Stoneblade", "value":0.11842105263157894},
    {"source": "Junk", "target": "Storm", "value":0.05095541402040651},
    {"source": "Junk", "target": "UR Delver", "value":0.10803324099722991},
    {"source": "Junk", "target": "UWx Control", "value":0.046875},
    {"source": "Junk", "target": "Zombie Bombardment", "value":0.13513513513513514},
    {"source": "Lands", "target": "Legacy Landstill", "value":0.01763224181400174},
    {"source": "Lands", "target": "LOAM", "value":0.2855740922491215},
    {"source": "Lands", "target": "Maverick", "value":0.20788177337125188},
    {"source": "Lands", "target": "Merfolk", "value":0.027667984190379476},
    {"source": "Lands", "target": "MUD", "value":0.07383419688456738},
    {"source": "Lands", "target": "Nic Fit", "value":0.08326253185117327},
    {"source": "Lands", "target": "Pikula", "value":0.10027472527115913},
    {"source": "Lands", "target": "Reanimator", "value":0.05063913474396033},
    {"source": "Lands", "target": "Stoneblade", "value":0.05921938089257656},
    {"source": "Lands", "target": "UR Delver", "value":0.08357348703699059},
    {"source": "Legacy Landstill", "target": "LOAM", "value":0.02097902097887427},
    {"source": "Legacy Landstill", "target": "Maverick", "value":0.046875000001831056},
    {"source": "Legacy Landstill", "target": "Merfolk", "value":0.10526315789473684},
    {"source": "Legacy Landstill", "target": "Nic Fit", "value":0.052238805963466244},
    {"source": "Legacy Landstill", "target": "Painter", "value":0.10256410256410256},
    {"source": "Legacy Landstill", "target": "Pikula", "value":0.06097560975609756},
    {"source": "Legacy Landstill", "target": "Slivers", "value":0.023809523809523808},
    {"source": "Legacy Landstill", "target": "Sneak & Show", "value":0.24660633485294117},
    {"source": "Legacy Landstill", "target": "Stoneblade", "value":0.486013986013986},
    {"source": "Legacy Landstill", "target": "Storm", "value":0.05095541402040651},
    {"source": "Legacy Landstill", "target": "UR Delver", "value":0.21212121212121213},
    {"source": "Legacy Landstill", "target": "UWx Control", "value":0.48558758314855877},
    {"source": "LOAM", "target": "Maverick", "value":0.30973451326211915},
    {"source": "LOAM", "target": "Merfolk", "value":0.03321033210307593},
    {"source": "LOAM", "target": "MUD", "value":0.07499999999946429},
    {"source": "LOAM", "target": "Nic Fit", "value":0.32478632480319963},
    {"source": "LOAM", "target": "Pikula", "value":0.22457627117415974},
    {"source": "LOAM", "target": "Reanimator", "value":0.08658008656468205},
    {"source": "LOAM", "target": "Slivers", "value":0.021428571428418367},
    {"source": "LOAM", "target": "Stoneblade", "value":0.08015267175511336},
    {"source": "LOAM", "target": "Storm", "value":0.03910614523721169},
    {"source": "LOAM", "target": "UR Delver", "value":0.09566639411205505},
    {"source": "LOAM", "target": "Zombie Bombardment", "value":0.0852713178372093},
    {"source": "Maverick", "target": "Merfolk", "value":0.04489795917697627},
    {"source": "Maverick", "target": "MUD", "value":0.09055118109734021},
    {"source": "Maverick", "target": "Nic Fit", "value":0.24347826087569},
    {"source": "Maverick", "target": "Pikula", "value":0.19909502262259166},
    {"source": "Maverick", "target": "Reanimator", "value":0.03652968035516357},
    {"source": "Maverick", "target": "Slivers", "value":0.031496062985243975},
    {"source": "Maverick", "target": "Stoneblade", "value":0.10494880546522818},
    {"source": "Maverick", "target": "UR Delver", "value":0.10909090909586777},
    {"source": "Maverick", "target": "UWx Control", "value":0.0381291306573718},
    {"source": "Merfolk", "target": "MUD", "value":0.11538461538461539},
    {"source": "Merfolk", "target": "Nic Fit", "value":0.04651162790805841},
    {"source": "Merfolk", "target": "Painter", "value":0.17142857142857143},
    {"source": "Merfolk", "target": "Pikula", "value":0.0375},
    {"source": "Merfolk", "target": "Slivers", "value":0.20588235294117646},
    {"source": "Merfolk", "target": "Sneak & Show", "value":0.09375000001269534},
    {"source": "Merfolk", "target": "Stoneblade", "value":0.1773255813953488},
    {"source": "Merfolk", "target": "Storm", "value":0.05050505051668197},
    {"source": "Merfolk", "target": "UR Delver", "value":0.10465116279069768},
    {"source": "Merfolk", "target": "UWx Control", "value":0.1706422018348624},
    {"source": "MUD", "target": "Nic Fit", "value":0.04301075268909701},
    {"source": "MUD", "target": "Painter", "value":0.2898550724637681},
    {"source": "MUD", "target": "Pikula", "value":0.07142857142857142},
    {"source": "MUD", "target": "Slivers", "value":0.07228915662650602},
    {"source": "MUD", "target": "Sneak & Show", "value":0.11534701855861426},
    {"source": "MUD", "target": "Stoneblade", "value":0.05769230769230768},
    {"source": "MUD", "target": "UR Delver", "value":0.09210526315789473},
    {"source": "Nic Fit", "target": "Pikula", "value":0.21304347824533085},
    {"source": "Nic Fit", "target": "Reanimator", "value":0.10550458714194931},
    {"source": "Nic Fit", "target": "Slivers", "value":0.06976744186208762},
    {"source": "Nic Fit", "target": "Sneak & Show", "value":0.025492468153187776},
    {"source": "Nic Fit", "target": "Stoneblade", "value":0.08161648176832993},
    {"source": "Nic Fit", "target": "Storm", "value":0.07530120482915699},
    {"source": "Nic Fit", "target": "UWx Control", "value":0.056400196167633546},
    {"source": "Nic Fit", "target": "Zombie Bombardment", "value":0.11570247932327028},
    {"source": "Painter", "target": "Sneak & Show", "value":0.2396313364027692},
    {"source": "Painter", "target": "Stoneblade", "value":0.12162162162162163},
    {"source": "Painter", "target": "Storm", "value":0.04901960785438293},
    {"source": "Painter", "target": "UR Delver", "value":0.05691056910569106},
    {"source": "Painter", "target": "UWx Control", "value":0.1595744680851064},
    {"source": "Pikula", "target": "Reanimator", "value":0.17647058822208242},
    {"source": "Pikula", "target": "Slivers", "value":0.024096385542168676},
    {"source": "Pikula", "target": "Stoneblade", "value":0.1506849315068493},
    {"source": "Pikula", "target": "Storm", "value":0.05853658536699584},
    {"source": "Pikula", "target": "UR Delver", "value":0.11267605633802817},
    {"source": "Pikula", "target": "UWx Control", "value":0.07467532467532467},
    {"source": "Pikula", "target": "Zombie Bombardment", "value":0.2028985507246377},
    {"source": "Reanimator", "target": "Sneak & Show", "value":0.05517503807942043},
    {"source": "Reanimator", "target": "Stoneblade", "value":0.06467661692151185},
    {"source": "Reanimator", "target": "Storm", "value":0.21493212664376243},
    {"source": "Reanimator", "target": "UR Delver", "value":0.09460946095085086},
    {"source": "Reanimator", "target": "UWx Control", "value":0.0659062103990323},
    {"source": "Reanimator", "target": "Zombie Bombardment", "value":0.388157894737621},
    {"source": "Sneak & Show", "target": "Stoneblade", "value":0.2894226104235924},
    {"source": "Sneak & Show", "target": "Storm", "value":0.1818443804385653},
    {"source": "Sneak & Show", "target": "UR Delver", "value":0.4088085826919908},
    {"source": "Sneak & Show", "target": "UWx Control", "value":0.29248340796801325},
    {"source": "Sneak & Show", "target": "Zombie Bombardment", "value":0.047904191639296254},
    {"source": "Stoneblade", "target": "Storm", "value":0.15722120659326425},
    {"source": "Stoneblade", "target": "UR Delver", "value":0.31399317406143334},
    {"source": "Stoneblade", "target": "UWx Control", "value":0.6982124079915877},
    {"source": "Stoneblade", "target": "Zombie Bombardment", "value":0.06578947368421052},
    {"source": "Storm", "target": "UR Delver", "value":0.22448979592907714},
    {"source": "Storm", "target": "UWx Control", "value":0.17035294118913064},
    {"source": "Storm", "target": "Zombie Bombardment", "value":0.2786885245708143},
    {"source": "UR Delver", "target": "UWx Control", "value":0.24742692466035401},
    {"source": "UR Delver", "target": "Zombie Bombardment", "value":0.07344632768361581},
    {"source": "UWx Control", "target": "Zombie Bombardment", "value":0.06867671691792294}
]}